tensorflow_reader.py
tensorflow_reader-1.0.6.dist-info/LICENSE
tensorflow_reader-1.0.6.dist-info/WHEEL
tensorflow_reader-1.0.6.dist-info/METADATA
tensorflow_reader-1.0.6.dist-info/RECORD
