Metadata-Version: 2.1
Name: tensorflow_reader
Version: 1.0.6
Summary: Whole-slide image file reader for TensorFlow
Home-page: https://github.com/DigitalSlideArchive/tensorflow_reader
License: UNKNOWN
Author: Lee Newberg
Author-email: lee.newberg@kitware.com
Classifier: License :: OSI Approved :: Apache Software License
